{
    "directed": false, 
    "graph": [], 
    "nodes": [
        {
            "party": "Republican", 
            "name": "Kristi L. Noem", 
            "id": "58189"
        }, 
        {
            "party": "Republican", 
            "name": "Francisco \"Quico\" Canseco", 
            "id": "50146"
        }, 
        {
            "party": "Republican", 
            "name": "Bob Corker", 
            "id": "65905"
        }, 
        {
            "party": "Republican", 
            "name": "Daniel Coats", 
            "id": "53291"
        }, 
        {
            "party": "Republican", 
            "name": "Phil Gingrey", 
            "id": "17644"
        }
    ], 
    "links": [
        {
            "source": "58189", 
            "target": "65905"
        }, 
        {
            "source": "58189", 
            "target": "17644"
        }, 
        {
            "source": "50146", 
            "target": "53291"
        }
    ], 
    "multigraph": false
}